README.md
setup.py
vscode/__init__.py
vscode/compiler.py
vscode/config.py
vscode/data.py
vscode/env_methods.py
vscode/extension.py
vscode/main.js
vscode/themes.py
vscode/types.py
vscode/undef.py
vscode/utils.py
vscode/webviews.py
vscode/window.py
vscode_ext.egg-info/PKG-INFO
vscode_ext.egg-info/SOURCES.txt
vscode_ext.egg-info/dependency_links.txt
vscode_ext.egg-info/top_level.txt