Metadata-Version: 2.1
Name: vscode-ext
Version: 1.5.4
Summary: Create VSCode Extensions with python
Home-page: https://github.com/CodeWithSwastik/vscode-ext
Author: Swas.py
Author-email: cwswas.py@gmail.com
License: UNKNOWN
Project-URL: Issue tracker, https://github.com/CodeWithSwastik/vscode-ext/issues
Platform: UNKNOWN
Classifier: Programming Language :: Python :: 3
Classifier: Intended Audience :: Developers
Classifier: License :: OSI Approved :: MIT License
Classifier: Operating System :: OS Independent
Classifier: Topic :: Internet
Classifier: Topic :: Software Development :: Libraries
Classifier: Topic :: Software Development :: Libraries :: Python Modules
Classifier: Topic :: Utilities
Requires-Python: >=3.6
